[
    {
    "channelName": "Cinemax ActionMax",
    "tvgName": "VIP US: Cinemax 5 Star Max",
    "tvgId": "ActionMAX.HDTV.(East).(AMXHD).us",
    "tvgLogo": "https://github.com/tv-logo/tv-logos/raw/main/countries/united-states/cinemax-actionmax-us.png",
    "extGrp": "Movies",
    "tvgShift": 0,
    "channelId": 10700
    },
    {
    "channelName": "Cinemax ActionMax",
    "tvgName": "VIP US: Cinemax ActionMax",
    "tvgId": "ActionMAX.HDTV.(East).(AMXHD).us",
    "tvgLogo": "https://github.com/tv-logo/tv-logos/raw/main/countries/united-states/cinemax-actionmax-us.png",
    "extGrp": "Movies",
    "tvgShift": 0,
    "channelId": 10720
    },
    {
    "channelName": "Cinemax ActionMax",
    "tvgName": "VIP US: Cinemax East",
    "tvgId": "ActionMAX.HDTV.(East).(AMXHD).us",
    "tvgLogo": "https://github.com/tv-logo/tv-logos/raw/main/countries/united-states/cinemax-actionmax-us.png",
    "extGrp": "Movies",
    "tvgShift": 0,
    "channelId": 10721
    },
    {
    "channelName": "Cinemax (West)",
    "tvgName": "VIP US: Cinemax Moremax",
    "tvgId": "Cinemax.HDTV.(West).(MAXHDW).us",
    "tvgLogo": "https://github.com/tv-logo/tv-logos/raw/main/countries/united-states/cinemax-us.png",
    "extGrp": "Live: USA",
    "tvgShift": 0,
    "channelId": 10693
    },
    {
    "channelName": "Cinemax MoreMax (West)",
    "tvgName": "VIP US: Cinemax Thrillermax",
    "tvgId": "More.Max.(East).(MOMAX).us",
    "tvgLogo": "https://github.com/tv-logo/tv-logos/raw/main/countries/united-states/cinemax-moremax-us.png",
    "extGrp": "Live: USA",
    "tvgShift": 3,
    "channelId": 30734
    }
]
